bitcoin_value/__init__.py
bitcoin_value/bitcoin_value.py
bitcoin_value-1.6.0.dist-info/LICENSE
bitcoin_value-1.6.0.dist-info/METADATA
bitcoin_value-1.6.0.dist-info/WHEEL
bitcoin_value-1.6.0.dist-info/top_level.txt
bitcoin_value-1.6.0.dist-info/RECORD
