Metadata-Version: 2.1
Name: bitcoin-value
Version: 1.6.0
Summary: A module to fetch the latest value of Bitcoin in different currencies.
Home-page: https://github.com/dewittethomas/bitcoin-value
Author: Thomas Dewitte
Author-email: thomasdewittecontact@gmail.com
License: MIT
Keywords: bitcoin currency value worth btc usd eur gbp crypto fetch
Classifier: Programming Language :: Python :: 3
Classifier: Programming Language :: Python :: 3.8
Classifier: Operating System :: OS Independent
Classifier: License :: OSI Approved :: MIT License
License-File: LICENSE
Requires-Dist: requests >=2.28.1
